esmlouvy_connector/__init__.py
esmlouvy_connector/api_client.py
esmlouvy_connector/configuration.py
esmlouvy_connector/rest.py
esmlouvy_connector/api/__init__.py
esmlouvy_connector/api/admins_api.py
esmlouvy_connector/api/attachments_api.py
esmlouvy_connector/api/developers_api.py
esmlouvy_connector/api/names_api.py
esmlouvy_connector/api/public_api.py
esmlouvy_connector/models/__init__.py
esmlouvy_connector/models/address.py
esmlouvy_connector/models/base_domino_document.py
esmlouvy_connector/models/base_sheet_document.py
esmlouvy_connector/models/budget_category.py
esmlouvy_connector/models/choice.py
esmlouvy_connector/models/company.py
esmlouvy_connector/models/config_body.py
esmlouvy_connector/models/container.py
esmlouvy_connector/models/cover_sheet.py
esmlouvy_connector/models/document_acl.py
esmlouvy_connector/models/document_attachment.py
esmlouvy_connector/models/document_attachment_entry.py
esmlouvy_connector/models/document_attachment_list.py
esmlouvy_connector/models/document_entry.py
esmlouvy_connector/models/document_entry_list.py
esmlouvy_connector/models/document_header.py
esmlouvy_connector/models/document_hidden.py
esmlouvy_connector/models/document_workflow.py
esmlouvy_connector/models/domino_commons.py
esmlouvy_connector/models/general_acl.py
esmlouvy_connector/models/payment_event.py
esmlouvy_connector/models/profile_directory.py
esmlouvy_connector/models/profile_main.py
esmlouvy_connector/models/profile_roles.py
esmlouvy_connector/models/registration_sheet.py
esmlouvy_connector/models/replace_name.py
esmlouvy_connector/models/standpoint.py
test/__init__.py
test/test_address.py
test/test_admins_api.py
test/test_attachments_api.py
test/test_base_domino_document.py
test/test_base_sheet_document.py
test/test_budget_category.py
test/test_choice.py
test/test_company.py
test/test_config_body.py
test/test_container.py
test/test_cover_sheet.py
test/test_developers_api.py
test/test_document_acl.py
test/test_document_attachment.py
sysnet_esmlouvy-1.1.1.dist-info/LICENSE
sysnet_esmlouvy-1.1.1.dist-info/METADATA
sysnet_esmlouvy-1.1.1.dist-info/WHEEL
sysnet_esmlouvy-1.1.1.dist-info/top_level.txt
sysnet_esmlouvy-1.1.1.dist-info/RECORD
